camphr/.gitignore
camphr/VERSION.py
camphr/__init__.py
camphr/doc.py
camphr/ner_labels/Makefile
camphr/ner_labels/__init__.py
camphr/ner_labels/ene.yml
camphr/ner_labels/labels_ene.py
camphr/ner_labels/labels_irex.py
camphr/ner_labels/labels_ontonotes.py
camphr/ner_labels/labels_wikipedia.py
camphr/ner_labels/ontonotes.yml
camphr/ner_labels/package.json
camphr/ner_labels/sekine.yml
camphr/ner_labels/utils.py
camphr/ner_labels/wikipedia.yml
camphr/nlp.py
camphr/pipe.py
camphr/py.typed
camphr/serde.py
camphr/tokenizer/__init__.py
camphr/tokenizer/juman/__init__.py
camphr/tokenizer/mecab/__init__.py
camphr/tokenizer/mecab/tag_map.py
camphr/tokenizer/sentencepiece/__init__.py
camphr/tokenizer/stop_words.py
camphr/utils.py
camphr-0.10.0.dist-info/entry_points.txt
camphr-0.10.0.dist-info/WHEEL
camphr-0.10.0.dist-info/METADATA
camphr-0.10.0.dist-info/RECORD
